skyto/__init__.py
skyto/ai_modules.py
skyto/cli.py
skyto/interpreter.py
skyto-0.4.dist-info/METADATA
skyto-0.4.dist-info/WHEEL
skyto-0.4.dist-info/entry_points.txt
skyto-0.4.dist-info/top_level.txt
skyto-0.4.dist-info/RECORD
