Metadata-Version: 2.4
Name: skyto
Version: 0.4
Summary: Skyto est un langage de programmation pédagogique basé sur Python, permettant d’écrire du code en Lingala et faire de l’intelligence artificielle
Author: Lanscky Tshinkola
Classifier: Programming Language :: Python :: 3
Requires-Python: >=3.6
Dynamic: author
Dynamic: classifier
Dynamic: requires-python
Dynamic: summary
